<?xml version="1.0" encoding="UTF-8"?>
<tutorial name="Actions" autoCloseWindowsInRightStage="true" autoClearAdhocResults="true">
	<!--flowRestriction>forwardexploration</flowRestriction-->
	<pageList>
		<page name="Actions part 1: Table xml basics" type="general">
			<contentFile>actionOneOfOne.html</contentFile>
			<SQLFile>blank.sql</SQLFile>
			<autoLoadLink>
				<pageWindow target="tabledef" raiseToTop="y">
					<panel name="top" PrimaryContainer="true">
		   				<link type="other" target="_self" window="_self" connectionRequired="y">
							<address>
								?BASE_DIRECTORY?/other/atsBaseView29.html
							</address>
						</link>
					</panel>
				</pageWindow>
			</autoLoadLink>
		</page>
		<page name="Actions part 1: The script" type="general">
			<contentFile>actionOneOfTwo.html</contentFile>
			<SQLFile>blank.sql</SQLFile>
			<autoLoadLink>
				<pageWindow target="tabledef" raiseToTop="y">
					<panel name="top" PrimaryContainer="true">
		   				<link type="other" target="_self" window="_self" connectionRequired="y">
							<address>
								?BASE_DIRECTORY?/other/atsBaseView28.html
							</address>
						</link>
					</panel>
				</pageWindow>
			</autoLoadLink>
		</page>
		<page name="Actions part 1: Follow-on actions" type="general">
			<contentFile>actionOneOfThree.html</contentFile>
			<SQLFile>blank.sql</SQLFile>
			<autoLoadLink>
				<pageWindow target="tabledef" raiseToTop="y">
					<panel name="top" PrimaryContainer="true">
		   				<link type="other" target="_self" window="_self" connectionRequired="y">
							<address>
								?BASE_DIRECTORY?/other/atsBaseView27.html
							</address>
						</link>
					</panel>
				</pageWindow>
			</autoLoadLink>
		</page>
		<page name="Actions part 1: Local vs. shared parameter and block values" type="general">
			<contentFile>actionOneOfFour.html</contentFile>
			<SQLFile>blank.sql</SQLFile>
			<autoLoadLink>
				<pageWindow target="tabledef" raiseToTop="y">
					<panel name="top" PrimaryContainer="true">
		   				<link type="other" target="_self" window="_self" connectionRequired="y">
							<address>
								?BASE_DIRECTORY?/other/atsBaseView26.html
							</address>
						</link>
					</panel>
				</pageWindow>
			</autoLoadLink>
		</page>
		<page name="Actions part 1: Loading pages" type="general">
			<contentFile>actionOneOfFive.html</contentFile>
			<SQLFile>blank.sql</SQLFile>
			<autoLoadLink>
				<pageWindow target="tabledef" raiseToTop="y">
					<panel name="top" PrimaryContainer="true">
		   				<link type="other" target="_self" window="_self" connectionRequired="y">
							<address>
								?BASE_DIRECTORY?/other/atsBaseView25.html
							</address>
						</link>
					</panel>
				</pageWindow>
			</autoLoadLink>
		</page>
		<page name="Actions part 2: Deleting a task" type="general">
			<contentFile>actionTwoOfOne.html</contentFile>
			<SQLFile>blank.sql</SQLFile>
			<autoLoadLink>
				<pageWindow target="tabledef" raiseToTop="y">
					<panel name="top" PrimaryContainer="true">
		   				<link type="other" target="_self" window="_self" connectionRequired="y">
							<address>
								?BASE_DIRECTORY?/other/atsBaseView24.html
							</address>
						</link>
					</panel>
				</pageWindow>
			</autoLoadLink>
		</page>
		<page name="Actions part 2: Start the delete script" type="general">
			<contentFile>actionTwoOfTwo.html</contentFile>
			<SQLFile>blank.sql</SQLFile>
			<autoLoadLink>
				<pageWindow target="tabledef" raiseToTop="y">
					<panel name="top" PrimaryContainer="true">
		   				<link type="other" target="_self" window="_self" connectionRequired="y">
							<address>
								?BASE_DIRECTORY?/other/atsBaseView23.html
							</address>
						</link>
					</panel>
				</pageWindow>
			</autoLoadLink>
		</page>
		<page name="Actions part 2: Delete confirmation" type="general">
			<contentFile>actionTwoOfThree.html</contentFile>
			<SQLFile>blank.sql</SQLFile>
			<autoLoadLink>
				<pageWindow target="tabledef" raiseToTop="y">
					<panel name="top" PrimaryContainer="true">
		   				<link type="other" target="_self" window="_self" connectionRequired="y">
							<address>
								?BASE_DIRECTORY?/other/atsBaseView22.html
							</address>
						</link>
					</panel>
				</pageWindow>
			</autoLoadLink>
		</page>
		<page name="Actions part 2: Completing the Delete" type="general">
			<contentFile>actionTwoOfFour.html</contentFile>
			<SQLFile>blank.sql</SQLFile>
			<autoLoadLink>
				<pageWindow target="tabledef" raiseToTop="y">
					<panel name="top" PrimaryContainer="true">
		   				<link type="other" target="_self" window="_self" connectionRequired="y">
							<address>
								?BASE_DIRECTORY?/other/atsBaseView21.html
							</address>
						</link>
					</panel>
				</pageWindow>
			</autoLoadLink>
		</page>
		<page name="Actions part 2: Catching errors from executeSQL" type="general">
			<contentFile>actionTwoOfFive.html</contentFile>
			<SQLFile>blank.sql</SQLFile>
			<autoLoadLink>
				<pageWindow target="tabledef" raiseToTop="y">
					<panel name="top" PrimaryContainer="true">
		   				<link type="other" target="_self" window="_self" connectionRequired="y">
							<address>
								?BASE_DIRECTORY?/other/atsBaseView20.html
							</address>
						</link>
					</panel>
				</pageWindow>
			</autoLoadLink>
		</page>
		<page name="Actions part 3: Editing a task" type="general">
			<contentFile>actionThreeOfOne.html</contentFile>
			<SQLFile>blank.sql</SQLFile>
			<autoLoadLink>
				<pageWindow target="tabledef" raiseToTop="y">
					<panel name="top" PrimaryContainer="true">
		   				<link type="other" target="_self" window="_self" connectionRequired="y">
							<address>
								?BASE_DIRECTORY?/other/atsBaseView19.html
							</address>
						</link>
					</panel>
				</pageWindow>
			</autoLoadLink>
		</page>
		<page name="Actions part 3: Retrieve row information for editing" type="general">
			<contentFile>actionThreeOfTwo.html</contentFile>
			<SQLFile>blank.sql</SQLFile>
			<autoLoadLink>
				<pageWindow target="tabledef" raiseToTop="y">
					<panel name="top" PrimaryContainer="true">
		   				<link type="other" target="_self" window="_self" connectionRequired="y">
							<address>
								?BASE_DIRECTORY?/other/atsBaseView18.html
							</address>
						</link>
					</panel>
				</pageWindow>
			</autoLoadLink>
		</page>
		<page name="Actions part 3: Server side parameter replacement" type="general">
			<contentFile>actionThreeOfThree.html</contentFile>
			<SQLFile>blank.sql</SQLFile>
			<autoLoadLink>
				<pageWindow target="tabledef" raiseToTop="y">
					<panel name="top" PrimaryContainer="true">
		   				<link type="other" target="_self" window="_self" connectionRequired="y">
							<address>
								?BASE_DIRECTORY?/other/atsBaseView17.html
							</address>
						</link>
					</panel>
				</pageWindow>
			</autoLoadLink>
		</page>
		<page name="Actions part 3: Retrieving Data from execute SQL" type="general">
			<contentFile>actionThreeOfFour.html</contentFile>
			<SQLFile>blank.sql</SQLFile>
			<autoLoadLink>
				<pageWindow target="tabledef" raiseToTop="y">
					<panel name="top" PrimaryContainer="true">
		   				<link type="other" target="_self" window="_self" connectionRequired="y">
							<address>
								?BASE_DIRECTORY?/other/atsBaseView16.html
							</address>
						</link>
					</panel>
				</pageWindow>
				<pageWindow target="xmldeff" raiseToTop="false">
					<panel name="top" PrimaryContainer="true">
		   				<link type="other" target="_self" window="_self" connectionRequired="y">
							<address>
<![CDATA[
								http://?DB2MC_SERVER?/?ACTION_PROCESSOR??action=viewXML&table=AdminTask%2FatsTaskEdit
]]>
							</address>
						</link>
					</panel>
				</pageWindow>
			</autoLoadLink>
		</page>
		<page name="Actions part 3: Building a form" type="general">
			<contentFile>actionThreeOfFive.html</contentFile>
			<SQLFile>blank.sql</SQLFile>
			<autoLoadLink>
				<pageWindow target="tabledef" raiseToTop="y">
					<panel name="top" PrimaryContainer="true">
		   				<link type="other" target="_self" window="_self" connectionRequired="y">
							<address>
								?BASE_DIRECTORY?/other/atsBaseView15.html
							</address>
						</link>
					</panel>
				</pageWindow>
			</autoLoadLink>
		</page>
		<page name="Actions part 3: Submitting form data" type="general">
			<contentFile>actionThreeOfSix.html</contentFile>
			<SQLFile>blank.sql</SQLFile>
			<autoLoadLink>
				<pageWindow target="tabledef" raiseToTop="y">
					<panel name="top" PrimaryContainer="true">
		   				<link type="other" target="_self" window="_self" connectionRequired="y">
							<address>
								?BASE_DIRECTORY?/other/atsBaseView14.html
							</address>
						</link>
					</panel>
				</pageWindow>
			</autoLoadLink>
		</page>
		<page name="Actions part 3: Setting up for parameter checks" type="general">
			<contentFile>actionThreeOfSeven.html</contentFile>
			<SQLFile>blank.sql</SQLFile>
			<autoLoadLink>
				<pageWindow target="tabledef" raiseToTop="y">
					<panel name="top" PrimaryContainer="true">
		   				<link type="other" target="_self" window="_self" connectionRequired="y">
							<address>
								?BASE_DIRECTORY?/other/atsBaseView13.html
							</address>
						</link>
					</panel>
				</pageWindow>
			</autoLoadLink>
		</page>
		<page name="Actions part 3: About parameter checks" type="general">
			<contentFile>actionThreeOfEight.html</contentFile>
			<SQLFile>blank.sql</SQLFile>
			<autoLoadLink>
				<pageWindow target="tabledef" raiseToTop="y">
					<panel name="top" PrimaryContainer="true">
		   				<link type="other" target="_self" window="_self" connectionRequired="y">
							<address>
								?BASE_DIRECTORY?/other/atsBaseView12.html
							</address>
						</link>
					</panel>
				</pageWindow>
			</autoLoadLink>
		</page>
		<page name="Actions part 3: Checks and tasks" type="general">
			<contentFile>actionThreeOfNine.html</contentFile>
			<SQLFile>blank.sql</SQLFile>
			<autoLoadLink>
				<pageWindow target="tabledef" raiseToTop="y">
					<panel name="top" PrimaryContainer="true">
		   				<link type="other" target="_self" window="_self" connectionRequired="y">
							<address>
								?BASE_DIRECTORY?/other/atsBaseView11.html
							</address>
						</link>
					</panel>
				</pageWindow>
			</autoLoadLink>
		</page>
		<page name="Actions part 3: Checks and non matches" type="general">
			<contentFile>actionThreeOfTen.html</contentFile>
			<SQLFile>blank.sql</SQLFile>
			<autoLoadLink>
				<pageWindow target="tabledef" raiseToTop="y">
					<panel name="top" PrimaryContainer="true">
		   				<link type="other" target="_self" window="_self" connectionRequired="y">
							<address>
								?BASE_DIRECTORY?/other/atsBaseView10.html
							</address>
						</link>
					</panel>
				</pageWindow>
			</autoLoadLink>
		</page>
		<page name="Actions part 3: Next combining begin date and time" type="general">
			<contentFile>actionThreeOfEleven.html</contentFile>
			<SQLFile>blank.sql</SQLFile>
			<autoLoadLink>
				<pageWindow target="tabledef" raiseToTop="y">
					<panel name="top" PrimaryContainer="true">
		   				<link type="other" target="_self" window="_self" connectionRequired="y">
							<address>
								?BASE_DIRECTORY?/other/atsBaseView9.html
							</address>
						</link>
					</panel>
				</pageWindow>
			</autoLoadLink>
		</page>
		<page name="Actions part 3: Begin date time checks" type="general">
			<contentFile>actionThreeOfTwelve.html</contentFile>
			<SQLFile>blank.sql</SQLFile>
			<autoLoadLink>
				<pageWindow target="tabledef" raiseToTop="y">
					<panel name="top" PrimaryContainer="true">
		   				<link type="other" target="_self" window="_self" connectionRequired="y">
							<address>
								?BASE_DIRECTORY?/other/atsBaseView8.html
							</address>
						</link>
					</panel>
				</pageWindow>
			</autoLoadLink>
		</page>
		<page name="Actions part 3: End date and time" type="general">
			<contentFile>actionThreeOfThirteen.html</contentFile>
			<SQLFile>blank.sql</SQLFile>
			<autoLoadLink>
				<pageWindow target="tabledef" raiseToTop="y">
					<panel name="top" PrimaryContainer="true">
		   				<link type="other" target="_self" window="_self" connectionRequired="y">
							<address>
								?BASE_DIRECTORY?/other/atsBaseView7.html
							</address>
						</link>
					</panel>
				</pageWindow>
			</autoLoadLink>
		</page>
		<page name="Actions part 3: Checking the schedule" type="general">
			<contentFile>actionThreeOfFourteen.html</contentFile>
			<SQLFile>blank.sql</SQLFile>
			<autoLoadLink>
				<pageWindow target="tabledef" raiseToTop="y">
					<panel name="top" PrimaryContainer="true">
		   				<link type="other" target="_self" window="_self" connectionRequired="y">
							<address>
								?BASE_DIRECTORY?/other/atsBaseView6.html
							</address>
						</link>
					</panel>
				</pageWindow>
			</autoLoadLink>
		</page>
		<page name="Actions part 3: Checking for return errors" type="general">
			<contentFile>actionThreeOfFifteen.html</contentFile>
			<SQLFile>blank.sql</SQLFile>
			<autoLoadLink>
				<pageWindow target="tabledef" raiseToTop="y">
					<panel name="top" PrimaryContainer="true">
		   				<link type="other" target="_self" window="_self" connectionRequired="y">
							<address>
								?BASE_DIRECTORY?/other/atsBaseView5.html
							</address>
						</link>
					</panel>
				</pageWindow>
			</autoLoadLink>
		</page>
		<page name="Actions part 4: Create a panel menu" type="general">
			<contentFile>actionFourOfOne.html</contentFile>
			<SQLFile>blank.sql</SQLFile>
			<autoLoadLink>
				<pageWindow target="tabledef" raiseToTop="y">
					<panel name="top" PrimaryContainer="true">
		   				<link type="other" target="_self" window="_self" connectionRequired="y">
							<address>
								?BASE_DIRECTORY?/other/atsBaseView4.html
							</address>
						</link>
					</panel>
				</pageWindow>
			</autoLoadLink>
		</page>
		<page name="Actions part 4: Add action script" type="general">
			<contentFile>actionFourOfTwo.html</contentFile>
			<SQLFile>blank.sql</SQLFile>
			<autoLoadLink>
				<pageWindow target="tabledef" raiseToTop="y">
					<panel name="top" PrimaryContainer="true">
		   				<link type="other" target="_self" window="_self" connectionRequired="y">
							<address>
								?BASE_DIRECTORY?/other/atsBaseView2.html
							</address>
						</link>
					</panel>
				</pageWindow>
			</autoLoadLink>
		</page>
		<page name="Actions part 4: Finishing the add action" type="general">
			<contentFile>actionFourOfThree.html</contentFile>
			<SQLFile>blank.sql</SQLFile>
			<autoLoadLink>
				<pageWindow target="tabledef" raiseToTop="y">
					<panel name="top" PrimaryContainer="true">
		   				<link type="other" target="_self" window="_self" connectionRequired="y">
							<address>
								?BASE_DIRECTORY?/other/atsBaseView.html
							</address>
						</link>
					</panel>
				</pageWindow>
			</autoLoadLink>
		</page>		
	</pageList>	
</tutorial>
